pre_commit_docker.py
pre_commit_docker-4.2.0.dist-info/METADATA
pre_commit_docker-4.2.0.dist-info/WHEEL
pre_commit_docker-4.2.0.dist-info/entry_points.txt
pre_commit_docker-4.2.0.dist-info/top_level.txt
pre_commit_docker-4.2.0.dist-info/RECORD
